{
  "project_info": {
    "project_number": "666341752669",
    "firebase_url": "https://campusfinder-6c74d-default-rtdb.asia-southeast1.firebasedatabase.app",
    "project_id": "campusfinder-6c74d",
    "storage_bucket": "campusfinder-6c74d.appspot.com"
  },
  "client": [
    {
      "client_info": {
        "mobilesdk_app_id": "1:666341752669:android:872996911b05199d1bb2b4",
        "android_client_info": {
          "package_name": "com.campusfinder"
        }
      },
      "oauth_client": [
        {
          "client_id": "666341752669-d1lnd0q52v81rebvc00emfk4enu4caeu.apps.googleusercontent.com",
          "client_type": 3
        }
      ],
      "api_key": [
        {
          "current_key": "AIzaSyAYDvdgPZdPJIxb8-nliIDupR6yVYBqcZg"
        }
      ],
      "services": {
        "appinvite_service": {
          "other_platform_oauth_client": [
            {
              "client_id": "666341752669-d1lnd0q52v81rebvc00emfk4enu4caeu.apps.googleusercontent.com",
              "client_type": 3
            }
          ]
        }
      }
    }
  ],
  "configuration_version": "1"
}